installkernel_wsl/__init__.py
installkernel_wsl/__main__.py
installkernel_wsl/main.py
installkernel_wsl/py.typed
installkernel_wsl/utils.py
installkernel_wsl-0.0.4.dist-info/METADATA
installkernel_wsl-0.0.4.dist-info/WHEEL
installkernel_wsl-0.0.4.dist-info/entry_points.txt
installkernel_wsl-0.0.4.dist-info/licenses/LICENSE.txt
installkernel_wsl-0.0.4.dist-info/RECORD
