Metadata-Version: 2.4
Name: installkernel-wsl
Version: 0.0.4
Summary: Script and installkernel hook to copy Linux kernel to the host system and update .wslconfig.
License-Expression: MIT
License-File: LICENSE.txt
Keywords: command line,wsl
Author: Andrew Udvare
Author-email: audvare@gmail.com
Requires-Python: >=3.10,<4.0
Classifier: Development Status :: 4 - Beta
Classifier: Intended Audience :: Developers
Classifier: Programming Language :: Python
Classifier: Programming Language :: Python :: 3.10
Classifier: Programming Language :: Python :: 3.11
Classifier: Programming Language :: Python :: 3.12
Classifier: Programming Language :: Python :: 3.13
Classifier: Programming Language :: Python :: 3.14
Classifier: Typing :: Typed
Requires-Dist: bascom (>=0.1.0,<0.2.0)
Requires-Dist: click (>=8.3.1,<9.0.0)
Requires-Dist: typing-extensions (>=4.15.0,<5.0.0)
Project-URL: Documentation, https://installkernel-wsl.readthedocs.org
Project-URL: Homepage, https://tatsh.github.io/installkernel-wsl/
Project-URL: Issues, https://github.com/Tatsh/installkernel-wsl/issues
Project-URL: Repository, https://github.com/Tatsh/installkernel-wsl
